fenix_mcp/__init__.py
fenix_mcp/main.py
fenix_mcp/application/presenters.py
fenix_mcp/application/tool_base.py
fenix_mcp/application/tool_registry.py
fenix_mcp/application/tools/__init__.py
fenix_mcp/application/tools/health.py
fenix_mcp/application/tools/initialize.py
fenix_mcp/application/tools/intelligence.py
fenix_mcp/application/tools/knowledge.py
fenix_mcp/application/tools/productivity.py
fenix_mcp/application/tools/user_config.py
fenix_mcp/domain/initialization.py
fenix_mcp/domain/intelligence.py
fenix_mcp/domain/knowledge.py
fenix_mcp/domain/productivity.py
fenix_mcp/domain/user_config.py
fenix_mcp/infrastructure/config.py
fenix_mcp/infrastructure/context.py
fenix_mcp/infrastructure/http_client.py
fenix_mcp/infrastructure/logging.py
fenix_mcp/infrastructure/fenix_api/client.py
fenix_mcp/interface/mcp_server.py
fenix_mcp/interface/transports.py
fenix_mcp-1.12.0.dist-info/METADATA
fenix_mcp-1.12.0.dist-info/WHEEL
fenix_mcp-1.12.0.dist-info/entry_points.txt
fenix_mcp-1.12.0.dist-info/top_level.txt
fenix_mcp-1.12.0.dist-info/RECORD
