Metadata-Version: 2.4
Name: fenix-mcp
Version: 1.12.0
Summary: Fênix Cloud MCP server implemented in Python
Author: Fenix Inc
Requires-Python: >=3.10
Requires-Dist: pydantic>=2.5
Requires-Dist: requests>=2.31
Requires-Dist: urllib3>=2.0
Requires-Dist: aiohttp>=3.9
Requires-Dist: pydantic-settings>=2.0
Provides-Extra: dev
Requires-Dist: pytest>=7.4; extra == "dev"
Requires-Dist: pytest-asyncio>=0.23; extra == "dev"
Requires-Dist: pytest-cov>=4.0; extra == "dev"
Requires-Dist: black>=23.0; extra == "dev"
Requires-Dist: flake8>=6.0; extra == "dev"
Requires-Dist: mypy>=1.0; extra == "dev"
Requires-Dist: twine>=4.0; extra == "dev"
